agent_coder/__init__.py
agent_coder/agent.py
agent_coder/chat_api.py
agent_coder/data_struct.py
agent_coder/file_exec.py
agent_coder/program_exec.py
agent_coder/tool.py
agent_coder-0.1.2.dist-info/METADATA
agent_coder-0.1.2.dist-info/WHEEL
agent_coder-0.1.2.dist-info/top_level.txt
agent_coder-0.1.2.dist-info/RECORD
