Metadata-Version: 2.4
Name: agent_coder
Version: 0.1.2
Summary: 一个具有程序执行监控和中断功能的 AI 代码构建智能体
Author-email: Zed <none@example.com>
Requires-Python: >=3.8
Requires-Dist: openai>=1.0.0
